{
  "project_info": {
    "project_number": "405031455387",
    "firebase_url": "https://doctrackuser.firebaseio.com",
    "project_id": "doctrackuser",
    "storage_bucket": "doctrackuser.appspot.com"
  },
  "client": [
    {
      "client_info": {
        "mobilesdk_app_id": "1:405031455387:android:02f7e0afac0afe82",
        "android_client_info": {
          "package_name": "com.pln.www"
        }
      },
      "oauth_client": [
        {
          "client_id": "405031455387-opvbmjn8qljr3vk9lcb6grqof77npskp.apps.googleusercontent.com",
          "client_type": 1,
          "android_info": {
            "package_name": "com.pln.www",
            "certificate_hash": "4f97db447a45d0a541d551a2c4b15a9aaf796c7a"
          }
        },
        {
          "client_id": "405031455387-i3n78a3qior69b4nui49jmhfcgd5ettn.apps.googleusercontent.com",
          "client_type": 1,
          "android_info": {
            "package_name": "com.pln.www",
            "certificate_hash": "f0c0b68471a600c3b0216bb715318d04baf681aa"
          }
        },
        {
          "client_id": "405031455387-a69tpj05cl1smsr3ni3k5ve6tfo14vms.apps.googleusercontent.com",
          "client_type": 3
        }
      ],
      "api_key": [
        {
          "current_key": "AIzaSyDSnIuTR2eMd98Pfk3Hb9JwqB2DLSctZmQ"
        }
      ],
      "services": {
        "analytics_service": {
          "status": 1
        },
        "appinvite_service": {
          "status": 2,
          "other_platform_oauth_client": [
            {
              "client_id": "405031455387-a69tpj05cl1smsr3ni3k5ve6tfo14vms.apps.googleusercontent.com",
              "client_type": 3
            }
          ]
        },
        "ads_service": {
          "status": 2
        }
      }
    }
  ],
  "configuration_version": "1"
}